Workbook

Sheet Dashboard
B2: Revenue Review — Northstar Retail
B3: Northstar Retail · prepared 19 October 2026 · USD
B5: Revenue | D5: Gross margin | F5: Units | H5: Growth
B6: =SUM(Data!C4:C15) | D6: =IFERROR((SUM(Data!C4:C15)-SUM(Data!D4:D15))/SUM(Data!C4:C15),0) | F6: =SUM(Data!G4:G15) | H6: =IFERROR(Data!C15/Data!C4-1,0)
B7: Total recognised revenue | D7: Revenue less direct cost | F7: Units delivered | H7: First to last month
B10: Monthly performance
B11: Month | C11: Revenue | D11: Cost | E11: Margin | F11: Margin % | G11: Units | H11: Region
B12: 2026-01 | C12: 29041 | D12: 12197 | E12: =C12-D12 | F12: =IFERROR(E12/C12,0) | G12: 764 | H12: North
B13: 2026-02 | C13: 31180 | D13: 13469 | E13: =C13-D13 | F13: =IFERROR(E13/C13,0) | G13: 799 | H13: South
B14: 2026-03 | C14: 33320 | D14: 14794 | E14: =C14-D14 | F14: =IFERROR(E14/C14,0) | G14: 833 | H14: East
B15: 2026-04 | C15: 35459 | D15: 16169 | E15: =C15-D15 | F15: =IFERROR(E15/C15,0) | G15: 864 | H15: West
B16: 2026-05 | C16: 33999 | D16: 15911 | E16: =C16-D16 | F16: =IFERROR(E16/C16,0) | G16: 809 | H16: North
B17: 2026-06 | C17: 36138 | D17: 15177 | E17: =C17-D17 | F17: =IFERROR(E17/C17,0) | G17: 840 | H17: South
B18: 2026-07 | C18: 38278 | D18: 16536 | E18: =C18-D18 | F18: =IFERROR(E18/C18,0) | G18: 1007 | H18: East
B19: 2026-08 | C19: 40418 | D19: 17945 | E19: =C19-D19 | F19: =IFERROR(E19/C19,0) | G19: 1036 | H19: West
B20: 2026-09 | C20: 38957 | D20: 17764 | E20: =C20-D20 | F20: =IFERROR(E20/C20,0) | G20: 973 | H20: North
B21: 2026-10 | C21: 41097 | D21: 19233 | E21: =C21-D21 | F21: =IFERROR(E21/C21,0) | G21: 1002 | H21: South
B22: 2026-11 | C22: 43236 | D22: 18159 | E22: =C22-D22 | F22: =IFERROR(E22/C22,0) | G22: 1029 | H22: East
B23: 2026-12 | C23: 45376 | D23: 19602 | E23: =C23-D23 | F23: =IFERROR(E23/C23,0) | G23: 1055 | H23: West
B24: Total | C24: =SUM(C12:C23) | D24: =SUM(D12:D23) | E24: =C24-D24 | F24: =IFERROR(E24/C24,0) | G24: =SUM(G12:G23)

Sheet Trend
A1: Margin % by month
A3: Month | B3: Margin %
A4: 2026-01 | B4: ='Dashboard'!F12
A5: 2026-02 | B5: ='Dashboard'!F13
A6: 2026-03 | B6: ='Dashboard'!F14
A7: 2026-04 | B7: ='Dashboard'!F15
A8: 2026-05 | B8: ='Dashboard'!F16
A9: 2026-06 | B9: ='Dashboard'!F17
A10: 2026-07 | B10: ='Dashboard'!F18
A11: 2026-08 | B11: ='Dashboard'!F19
A12: 2026-09 | B12: ='Dashboard'!F20
A13: 2026-10 | B13: ='Dashboard'!F21
A14: 2026-11 | B14: ='Dashboard'!F22
A15: 2026-12 | B15: ='Dashboard'!F23

Sheet Data
A1: Monthly performance
A2: Edit Revenue and Cost; every dashboard formula recalculates.
A3: Month | B3: Revenue | C3: Cost | D3: Margin | E3: Margin % | F3: Units | G3: Region | H3: Notes
A4: 2026-01 | B4: 29041 | C4: 12197 | D4: =C4-D4 | E4: =IFERROR(E4/C4,0) | F4: 764 | G4: North | H4: Baseline
A5: 2026-02 | B5: 31180 | C5: 13469 | D5: =C5-D5 | E5: =IFERROR(E5/C5,0) | F5: 799 | G5: South | H5: New listing
A6: 2026-03 | B6: 33320 | C6: 14794 | D6: =C6-D6 | E6: =IFERROR(E6/C6,0) | F6: 833 | G6: East | H6: Price test
A7: 2026-04 | B7: 35459 | C7: 16169 | D7: =C7-D7 | E7: =IFERROR(E7/C7,0) | F7: 864 | G7: West | H7: Campaign
A8: 2026-05 | B8: 33999 | C8: 15911 | D8: =C8-D8 | E8: =IFERROR(E8/C8,0) | F8: 809 | G8: North | H8: Baseline
A9: 2026-06 | B9: 36138 | C9: 15177 | D9: =C9-D9 | E9: =IFERROR(E9/C9,0) | F9: 840 | G9: South | H9: Campaign
A10: 2026-07 | B10: 38278 | C10: 16536 | D10: =C10-D10 | E10: =IFERROR(E10/C10,0) | F10: 1007 | G10: East | H10: New region
A11: 2026-08 | B11: 40418 | C11: 17945 | D11: =C11-D11 | E11: =IFERROR(E11/C11,0) | F11: 1036 | G11: West | H11: Baseline
A12: 2026-09 | B12: 38957 | C12: 17764 | D12: =C12-D12 | E12: =IFERROR(E12/C12,0) | F12: 973 | G12: North | H12: Price test
A13: 2026-10 | B13: 41097 | C13: 19233 | D13: =C13-D13 | E13: =IFERROR(E13/C13,0) | F13: 1002 | G13: South | H13: Campaign
A14: 2026-11 | B14: 43236 | C14: 18159 | D14: =C14-D14 | E14: =IFERROR(E14/C14,0) | F14: 1029 | G14: East | H14: Baseline
A15: 2026-12 | B15: 45376 | C15: 19602 | D15: =C15-D15 | E15: =IFERROR(E15/C15,0) | F15: 1055 | G15: West | H15: Year end

Sheet Assumptions
A1: Assumptions and controls
A3: Tax rate | B3: 0.08
A4: Growth assumption | B4: 0.12
A5: Cost inflation | B5: 0.04
A6: Units per day (plan) | B6: 10
A7: Contingency | B7: 0.1
A10: Notes
A11: All values are fictional and internally consistent for demonstration.
A12: Dashboard totals use live formulas; edits in Data recalculate the view.
A13: No external links, macros or cached secrets are present in this workbook.
A14: Workbook mode: revenue; chart series are bound to the table above.
